deepgram/__init__.py
deepgram/client.py
deepgram/errors.py
deepgram/options.py
deepgram/audio/__init__.py
deepgram/audio/microphone/__init__.py
deepgram/audio/microphone/constants.py
deepgram/audio/microphone/errors.py
deepgram/audio/microphone/microphone.py
deepgram/audio/speaker/__init__.py
deepgram/audio/speaker/constants.py
deepgram/audio/speaker/errors.py
deepgram/audio/speaker/speaker.py
deepgram/clients/__init__.py
deepgram/clients/agent_router.py
deepgram/clients/errors.py
deepgram/clients/listen_router.py
deepgram/clients/read_router.py
deepgram/clients/speak_router.py
deepgram/clients/agent/__init__.py
deepgram/clients/agent/client.py
deepgram/clients/agent/enums.py
deepgram/clients/agent/v1/__init__.py
deepgram/clients/agent/v1/websocket/__init__.py
deepgram/clients/agent/v1/websocket/async_client.py
deepgram/clients/agent/v1/websocket/client.py
deepgram/clients/agent/v1/websocket/options.py
deepgram/clients/agent/v1/websocket/response.py
deepgram/clients/analyze/__init__.py
deepgram/clients/analyze/client.py
deepgram/clients/analyze/v1/__init__.py
deepgram/clients/analyze/v1/async_client.py
deepgram/clients/analyze/v1/client.py
deepgram/clients/analyze/v1/helpers.py
deepgram/clients/analyze/v1/options.py
deepgram/clients/analyze/v1/response.py
deepgram/clients/common/__init__.py
deepgram/clients/common/v1/__init__.py
deepgram/clients/common/v1/abstract_async_rest.py
deepgram/clients/common/v1/abstract_async_websocket.py
deepgram/clients/common/v1/abstract_sync_rest.py
deepgram/clients/common/v1/abstract_sync_websocket.py
deepgram/clients/common/v1/enums.py
deepgram/clients/common/v1/errors.py
deepgram/clients/common/v1/helpers.py
deepgram/clients/common/v1/options.py
deepgram/clients/common/v1/rest_response.py
deepgram/clients/common/v1/shared_response.py
deepgram/clients/common/v1/websocket_events.py
deepgram/clients/common/v1/websocket_response.py
deepgram/clients/listen/__init__.py
deepgram/clients/listen/client.py
deepgram/clients/listen/enums.py
deepgram_unstable_sdk-3.8.0.dev4.dist-info/LICENSE
deepgram_unstable_sdk-3.8.0.dev4.dist-info/METADATA
deepgram_unstable_sdk-3.8.0.dev4.dist-info/WHEEL
deepgram_unstable_sdk-3.8.0.dev4.dist-info/top_level.txt
deepgram_unstable_sdk-3.8.0.dev4.dist-info/RECORD
