Metadata-Version: 2.1
Name: deepgram-unstable-sdk
Version: 3.8.0.dev4
Summary: The official Python SDK for the Deepgram automated speech recognition platform.
Home-page: https://github.com/deepgram/deepgram-python-sdk
Author: Deepgram
Author-email: devrel@deepgram.com
License: MIT
Keywords: deepgram,deepgram speech-to-text
Classifier: Intended Audience :: Developers
Classifier: License :: OSI Approved :: MIT License
Classifier: Programming Language :: Python :: 3
License-File: LICENSE
Requires-Dist: httpx>=0.25.2
Requires-Dist: websockets>=12.0
Requires-Dist: dataclasses-json>=0.6.3
Requires-Dist: typing-extensions>=4.9.0
Requires-Dist: aiohttp>=3.9.1
Requires-Dist: aiofiles>=23.2.1
Requires-Dist: aenum>=3.1.0
Requires-Dist: deprecation>=2.1.0
